keras_custom/__init__.py
keras_custom/gradient/__init__.py
keras_custom/gradient/grad.py
keras_custom/layers/__init__.py
keras_custom/layers/onnx.py
keras_custom/layers/typing.py
keras_custom/layers/activations/__init__.py
keras_custom/layers/activations/activation.py
keras_custom/layers/activations/pow.py
keras_custom/layers/cast/__init__.py
keras_custom/layers/cast/cast.py
keras_custom/layers/constant/__init__.py
keras_custom/layers/constant/constant.py
keras_custom/layers/constant/padding.py
keras_custom/layers/core/__init__.py
keras_custom/layers/core/linear.py
keras_custom/layers/normalization/__init__.py
keras_custom/layers/numpy/__init__.py
keras_custom/layers/numpy/ops.py
keras_custom/layers/reduce/__init__.py
keras_custom/layers/reduce/base_reduce.py
keras_custom/layers/reduce/max.py
keras_custom/layers/reduce/mean.py
keras_custom/layers/reduce/min.py
keras_custom/layers/reduce/normalization.py
keras_custom/layers/reduce/sum.py
keras_custom/layers/reshaping/__init__.py
keras_custom/layers/reshaping/reshaping.py
keras_custom/model/__init__.py
keras_custom/model/channel.py
keras_custom/model/fusion_models.py
keras_custom/model/nested_models.py
keras_custom/model/replace_layer.py
keras_custom/utils/__init__.py
keras_custom/utils/linear.py
keras_custom/utils/nested_models.py
keras_custom-0.1.1.dist-info/licenses/LICENSE
keras_custom-0.1.1.dist-info/METADATA
keras_custom-0.1.1.dist-info/WHEEL
keras_custom-0.1.1.dist-info/top_level.txt
keras_custom-0.1.1.dist-info/RECORD
