Metadata-Version: 2.4
Name: keras_custom
Version: 0.1.1
Summary: Custom Layers in keras 3
Author-email: melanie.ducoffe@airbus.com
Project-URL: documentation, https://ducoffeM.github.io/keras_custom
Project-URL: repository, https://github.com/ducoffeM/keras_custom
Requires-Python: >=3.9
License-File: LICENSE
Requires-Dist: keras>=3
Provides-Extra: dev
Requires-Dist: tox>=4.6.4; extra == "dev"
Dynamic: license-file
